[{"idUser": 0, "Recomandation": [[1, "./IMAGES/CHECKED/RECOM/Taipei%2C%20Taiwan%20CBD%20Skyline.jpg"], [2, "./IMAGES/CHECKED/RECOM/Lugano%20from%20Sighignola.jpg"], [11, "./IMAGES/CHECKED/RECOM/Palencia%20-%20panoramio%20%28cropped%29.jpg"]]}, {"idUser": 1, "Recomandation": [[3, "./IMAGES/CHECKED/RECOM/19-07-27-Wismar-Innenstadt-DJI%200058-Panorama-2.jpg"], [11, "./IMAGES/CHECKED/RECOM/Palencia%20-%20panoramio%20%28cropped%29.jpg"], [13, "./IMAGES/CHECKED/RECOM/Piazza%20Maggiore%20-%20Panoramica.jpg"]]}, {"idUser": 2, "Recomandation": [[1, "./IMAGES/CHECKED/RECOM/Taipei%2C%20Taiwan%20CBD%20Skyline.jpg"], [3, "./IMAGES/CHECKED/RECOM/19-07-27-Wismar-Innenstadt-DJI%200058-Panorama-2.jpg"], [11, "./IMAGES/CHECKED/RECOM/Palencia%20-%20panoramio%20%28cropped%29.jpg"], [12, "./IMAGES/CHECKED/RECOM/Bologna%20Panorama.jpg"]]}, {"idUser": 3, "Recomandation": [[2, "./IMAGES/CHECKED/RECOM/Lugano%20from%20Sighignola.jpg"], [3, "./IMAGES/CHECKED/RECOM/19-07-27-Wismar-Innenstadt-DJI%200058-Panorama-2.jpg"], [13, "./IMAGES/CHECKED/RECOM/Piazza%20Maggiore%20-%20Panoramica.jpg"]]}, {"idUser": 4, "Recomandation": [[1, "./IMAGES/CHECKED/RECOM/Taipei%2C%20Taiwan%20CBD%20Skyline.jpg"], [7, "./IMAGES/CHECKED/RECOM/Castello%20Aragonese%28Taranto%29.JPG"], [8, "./IMAGES/CHECKED/RECOM/Hoan%20Kiem%20Lake%20with%20Thap%20Rua%20%28Tortise%20Tower%29%20%283695178852%29.jpg"]]}]